example_package/__init__.py
example_package/example.py
dip.f50-0.0.2.dist-info/LICENSE
dip.f50-0.0.2.dist-info/METADATA
dip.f50-0.0.2.dist-info/WHEEL
dip.f50-0.0.2.dist-info/top_level.txt
dip.f50-0.0.2.dist-info/RECORD
