Metadata-Version: 2.1
Name: dip.f50
Version: 0.0.2
Summary: Prints name from userinput
Home-page: https://github.com/pypa/sampleproject
Author: Diptarka Das
Author-email: dip.f50@gmail.com
License: UNKNOWN
Project-URL: Bug Tracker, https://github.com/pypa/sampleproject/issues
Platform: UNKNOWN
Classifier: Programming Language :: Python :: 3
Classifier: License :: OSI Approved :: MIT License
Classifier: Operating System :: OS Independent
Requires-Python: >=3.6
License-File: LICENSE
